{
    "key": "group_64fea51d91f3c",
    "title": "Homepage Items",
    "fields": [
        {
            "key": "field_64fea51da168f",
            "label": "CPP Sections",
            "name": "cpp_sections",
            "aria-label": "",
            "type": "flexible_content",
            "instructions": "",
            "required": 0,
            "conditional_logic": 0,
            "wrapper": {
                "width": "",
                "class": "",
                "id": ""
            },
            "layouts": {
                "layout_64fef9bd5f222": {
                    "key": "layout_64fef9bd5f222",
                    "name": "hero",
                    "label": "Hero",
                    "display": "block",
                    "sub_fields": [
                        {
                            "key": "field_64fef9c75f224",
                            "label": "Hero Heading",
                            "name": "hero_heading",
                            "aria-label": "",
                            "type": "text",
                            "instructions": "",
                            "required": 0,
                            "conditional_logic": 0,
                            "wrapper": {
                                "width": "",
                                "class": "",
                                "id": ""
                            },
                            "default_value": "",
                            "maxlength": "",
                            "placeholder": "",
                            "prepend": "",
                            "append": ""
                        },
                        {
                            "key": "field_64fef9d85f225",
                            "label": "Hero Content",
                            "name": "hero_content",
                            "aria-label": "",
                            "type": "text",
                            "instructions": "",
                            "required": 0,
                            "conditional_logic": 0,
                            "wrapper": {
                                "width": "",
                                "class": "",
                                "id": ""
                            },
                            "default_value": "",
                            "maxlength": "",
                            "placeholder": "",
                            "prepend": "",
                            "append": ""
                        },
                        {
                            "key": "field_64fef9ea5f226",
                            "label": "Hero Buttons",
                            "name": "hero_buttons",
                            "aria-label": "",
                            "type": "button_group",
                            "instructions": "",
                            "required": 0,
                            "conditional_logic": 0,
                            "wrapper": {
                                "width": "",
                                "class": "",
                                "id": ""
                            },
                            "choices": {
                                "Contact Me": "Contact Me",
                                "Learn More": "Learn More"
                            },
                            "default_value": "",
                            "return_format": "value",
                            "allow_null": 0,
                            "layout": "horizontal"
                        },
                        {
                            "key": "field_64fefa285f227",
                            "label": "Hero Image",
                            "name": "hero_image",
                            "aria-label": "",
                            "type": "image",
                            "instructions": "",
                            "required": 0,
                            "conditional_logic": 0,
                            "wrapper": {
                                "width": "",
                                "class": "",
                                "id": ""
                            },
                            "return_format": "id",
                            "library": "all",
                            "min_width": "",
                            "min_height": "",
                            "min_size": "",
                            "max_width": "",
                            "max_height": "",
                            "max_size": "",
                            "mime_types": "",
                            "preview_size": "medium"
                        },
                        {
                            "key": "field_64fefa395f228",
                            "label": "Background Colour",
                            "name": "background_colour",
                            "aria-label": "",
                            "type": "color_picker",
                            "instructions": "",
                            "required": 0,
                            "conditional_logic": 0,
                            "wrapper": {
                                "width": "",
                                "class": "",
                                "id": ""
                            },
                            "default_value": "",
                            "enable_opacity": 1,
                            "return_format": "string"
                        }
                    ],
                    "min": "",
                    "max": ""
                },
                "layout_64fea77d6bc38": {
                    "key": "layout_64fea77d6bc38",
                    "name": "two_column",
                    "label": "Two Column",
                    "display": "block",
                    "sub_fields": [
                        {
                            "key": "field_64fea7e6a1690",
                            "label": "Column 1 Eyebrow",
                            "name": "column_1_eyebrow",
                            "aria-label": "",
                            "type": "text",
                            "instructions": "",
                            "required": 0,
                            "conditional_logic": 0,
                            "wrapper": {
                                "width": "20",
                                "class": "",
                                "id": ""
                            },
                            "default_value": "",
                            "maxlength": "",
                            "placeholder": "",
                            "prepend": "",
                            "append": ""
                        },
                        {
                            "key": "field_6501569125284",
                            "label": "Column 1 Icon",
                            "name": "column_1_icon",
                            "aria-label": "",
                            "type": "image",
                            "instructions": "",
                            "required": 0,
                            "conditional_logic": 0,
                            "wrapper": {
                                "width": "",
                                "class": "",
                                "id": ""
                            },
                            "return_format": "id",
                            "library": "all",
                            "min_width": "",
                            "min_height": "",
                            "min_size": "",
                            "max_width": "",
                            "max_height": "",
                            "max_size": "",
                            "mime_types": "",
                            "preview_size": "medium"
                        },
                        {
                            "key": "field_64fea8ddbe8b4",
                            "label": "Column 1 Heading",
                            "name": "column_1_heading",
                            "aria-label": "",
                            "type": "text",
                            "instructions": "",
                            "required": 0,
                            "conditional_logic": 0,
                            "wrapper": {
                                "width": "30",
                                "class": "",
                                "id": ""
                            },
                            "default_value": "",
                            "maxlength": "",
                            "placeholder": "",
                            "prepend": "",
                            "append": ""
                        },
                        {
                            "key": "field_64feaba71db35",
                            "label": "Column 1 Content",
                            "name": "column_1_content",
                            "aria-label": "",
                            "type": "wysiwyg",
                            "instructions": "",
                            "required": 0,
                            "conditional_logic": 0,
                            "wrapper": {
                                "width": "",
                                "class": "",
                                "id": ""
                            },
                            "default_value": "",
                            "tabs": "all",
                            "toolbar": "basic",
                            "media_upload": 1,
                            "delay": 0
                        },
                        {
                            "key": "field_64fef87402a9e",
                            "label": "Column 1 Image",
                            "name": "column_1_image",
                            "aria-label": "",
                            "type": "image",
                            "instructions": "",
                            "required": 0,
                            "conditional_logic": 0,
                            "wrapper": {
                                "width": "50",
                                "class": "",
                                "id": ""
                            },
                            "return_format": "id",
                            "library": "all",
                            "min_width": "",
                            "min_height": "",
                            "min_size": "",
                            "max_width": "",
                            "max_height": "",
                            "max_size": "",
                            "mime_types": "",
                            "preview_size": "medium"
                        },
                        {
                            "key": "field_64fea8fbbe8b5",
                            "label": "Column 1 Button Text",
                            "name": "column_1_button_text",
                            "aria-label": "",
                            "type": "text",
                            "instructions": "",
                            "required": 0,
                            "conditional_logic": 0,
                            "wrapper": {
                                "width": "15",
                                "class": "",
                                "id": ""
                            },
                            "default_value": "",
                            "maxlength": "",
                            "placeholder": "",
                            "prepend": "",
                            "append": ""
                        },
                        {
                            "key": "field_64fea932be8b6",
                            "label": "Column 1 Button Link",
                            "name": "column_1_button_link",
                            "aria-label": "",
                            "type": "link",
                            "instructions": "",
                            "required": 0,
                            "conditional_logic": 0,
                            "wrapper": {
                                "width": "30",
                                "class": "",
                                "id": ""
                            },
                            "return_format": "url"
                        },
                        {
                            "key": "field_64fef89a02a9f",
                            "label": "Column 2 Heading",
                            "name": "column_2_heading",
                            "aria-label": "",
                            "type": "text",
                            "instructions": "",
                            "required": 0,
                            "conditional_logic": 0,
                            "wrapper": {
                                "width": "30",
                                "class": "",
                                "id": ""
                            },
                            "default_value": "",
                            "maxlength": "",
                            "placeholder": "",
                            "prepend": "",
                            "append": ""
                        },
                        {
                            "key": "field_64fef85802a9d",
                            "label": "Column 2 Content",
                            "name": "column_2_content",
                            "aria-label": "",
                            "type": "wysiwyg",
                            "instructions": "",
                            "required": 0,
                            "conditional_logic": 0,
                            "wrapper": {
                                "width": "",
                                "class": "",
                                "id": ""
                            },
                            "default_value": "",
                            "tabs": "all",
                            "toolbar": "basic",
                            "media_upload": 1,
                            "delay": 0
                        },
                        {
                            "key": "field_64fea802a1691",
                            "label": "Column 2 Image",
                            "name": "column_2_image",
                            "aria-label": "",
                            "type": "image",
                            "instructions": "",
                            "required": 0,
                            "conditional_logic": 0,
                            "wrapper": {
                                "width": "50",
                                "class": "",
                                "id": ""
                            },
                            "return_format": "id",
                            "library": "all",
                            "min_width": "",
                            "min_height": "",
                            "min_size": "",
                            "max_width": "",
                            "max_height": "",
                            "max_size": "",
                            "mime_types": "",
                            "preview_size": "medium"
                        },
                        {
                            "key": "field_650170c96cd1f",
                            "label": "Background Colour",
                            "name": "background_colour",
                            "aria-label": "",
                            "type": "color_picker",
                            "instructions": "",
                            "required": 0,
                            "conditional_logic": 0,
                            "wrapper": {
                                "width": "",
                                "class": "",
                                "id": ""
                            },
                            "default_value": "",
                            "enable_opacity": 1,
                            "return_format": "string"
                        }
                    ],
                    "min": "",
                    "max": ""
                },
                "layout_64fefe28a7c2a": {
                    "key": "layout_64fefe28a7c2a",
                    "name": "therapy",
                    "label": "Therapy",
                    "display": "block",
                    "sub_fields": [
                        {
                            "key": "field_64fefdabc780a",
                            "label": "Therapy Icon",
                            "name": "therapy_icon",
                            "aria-label": "",
                            "type": "image",
                            "instructions": "",
                            "required": 0,
                            "conditional_logic": 0,
                            "wrapper": {
                                "width": "10",
                                "class": "",
                                "id": ""
                            },
                            "return_format": "id",
                            "library": "all",
                            "min_width": "",
                            "min_height": "",
                            "min_size": "",
                            "max_width": "",
                            "max_height": "",
                            "max_size": "",
                            "mime_types": "",
                            "preview_size": "medium"
                        },
                        {
                            "key": "field_64fefdcfc780b",
                            "label": "Therapy Heading",
                            "name": "therapy_heading",
                            "aria-label": "",
                            "type": "text",
                            "instructions": "",
                            "required": 0,
                            "conditional_logic": 0,
                            "wrapper": {
                                "width": "25",
                                "class": "",
                                "id": ""
                            },
                            "default_value": "",
                            "maxlength": "",
                            "placeholder": "",
                            "prepend": "",
                            "append": ""
                        },
                        {
                            "key": "field_64fefdddc780c",
                            "label": "Therapy Content",
                            "name": "therapy_content",
                            "aria-label": "",
                            "type": "textarea",
                            "instructions": "",
                            "required": 0,
                            "conditional_logic": 0,
                            "wrapper": {
                                "width": "40",
                                "class": "",
                                "id": ""
                            },
                            "default_value": "",
                            "maxlength": "",
                            "rows": "",
                            "placeholder": "",
                            "new_lines": ""
                        },
                        {
                            "key": "field_65010063be172",
                            "label": "Therapy Link",
                            "name": "therapy_link",
                            "aria-label": "",
                            "type": "link",
                            "instructions": "",
                            "required": 0,
                            "conditional_logic": 0,
                            "wrapper": {
                                "width": "",
                                "class": "",
                                "id": ""
                            },
                            "return_format": "url"
                        },
                        {
                            "key": "field_650171142b3a9",
                            "label": "Background Colour",
                            "name": "background_colour",
                            "aria-label": "",
                            "type": "color_picker",
                            "instructions": "",
                            "required": 0,
                            "conditional_logic": 0,
                            "wrapper": {
                                "width": "",
                                "class": "",
                                "id": ""
                            },
                            "default_value": "",
                            "enable_opacity": 1,
                            "return_format": "string"
                        }
                    ],
                    "min": "",
                    "max": ""
                }
            },
            "min": "",
            "max": "",
            "button_label": "Add Row"
        }
    ],
    "location": [
        [
            {
                "param": "post_category",
                "operator": "==",
                "value": "category:homepage"
            }
        ]
    ],
    "menu_order": 0,
    "position": "normal",
    "style": "default",
    "label_placement": "top",
    "instruction_placement": "label",
    "hide_on_screen": "",
    "active": true,
    "description": "",
    "show_in_rest": 0,
    "modified": 1694664967
}
